pq_peek/__init__.py
pq_peek/__main__.py
pq_peek/main.py
pq_peek/py.typed
pq_peek-0.1.1.dist-info/WHEEL
pq_peek-0.1.1.dist-info/entry_points.txt
pq_peek-0.1.1.dist-info/METADATA
pq_peek-0.1.1.dist-info/RECORD
