Metadata-Version: 2.3
Name: pq-peek
Version: 0.1.1
Summary: A blazing fast CLI tool to inspect Parquet files using Polars.
Author: Lars Lewerenz
Author-email: Lars Lewerenz <git.lars.lewerenz@gmail.com>
Requires-Dist: polars>=1.37.1
Requires-Dist: rich>=14.3.1
Requires-Dist: typer>=0.21.1
Requires-Python: >=3.12
